pyolov3/__init__.py
pyolov3/bbox.py
pyolov3/darknet.py
pyolov3/data/coco.names
pyolov3/data/face.names
pyolov3/data/openimages.names
pyolov3/data/pallete
pyolov3/data/yolov3-face.cfg
pyolov3/data/yolov3-openimages.cfg
pyolov3/data/yolov3.cfg
pyolov3/detector.py
pyolov3/util.py
pyolov3-0.1.2.dist-info/LICENSE
pyolov3-0.1.2.dist-info/WHEEL
pyolov3-0.1.2.dist-info/METADATA
pyolov3-0.1.2.dist-info/RECORD
