Metadata-Version: 2.1
Name: pyolov3
Version: 0.1.2
Summary: A PyTorch implementation of the YOLO v3 object detection algorithm
Home-page: https://github.com/reeve0930/pyolov3
License: MIT
Keywords: yolo,yolo-v3
Author: reeve0930
Author-email: reeve0930@gmail.com
Requires-Python: >=3.7,<4.0
Classifier: License :: OSI Approved :: MIT License
Classifier: Programming Language :: Python :: 3
Classifier: Programming Language :: Python :: 3.7
Classifier: Programming Language :: Python :: 3.8
Requires-Dist: matplotlib (>=3.2.1,<4.0.0)
Requires-Dist: opencv-python (>=4.2.0,<5.0.0)
Requires-Dist: torch (==1.4.0)
Requires-Dist: torchvision (==0.5.0)
Requires-Dist: wget (>=3.2,<4.0)
Project-URL: Repository, https://github.com/reeve0930/pyolov3
